examples/hf_integration.py
examples/quickstart.py
examples/validate_conformal.py
r3alai/__init__.py
r3alai/active_learning/__init__.py
r3alai/active_learning/active_learner.py
r3alai/conformal/__init__.py
r3alai/conformal/conformal_predictor.py
r3alai/models/__init__.py
r3alai/models/rsnn.py
r3alai/utils/__init__.py
r3alai/utils/integration.py
tests/test_basic.py
r3alai-0.1.3.dist-info/METADATA
r3alai-0.1.3.dist-info/WHEEL
r3alai-0.1.3.dist-info/top_level.txt
r3alai-0.1.3.dist-info/RECORD
