Metadata-Version: 2.4
Name: r3alai
Version: 0.1.3
Summary: A Python library for Random Set Neural Networks with uncertainty estimation
Home-page: https://github.com/R3AL-AI/package
Author: Arshia
Author-email: Arshia <arshia@r3al.ai>
License-Expression: MIT
Project-URL: Homepage, https://github.com/R3AL-AI/package
Project-URL: Documentation, https://github.com/R3AL-AI/package#readme
Project-URL: Issues, https://github.com/R3AL-AI/package/issues
Project-URL: Source, https://github.com/R3AL-AI/package
Classifier: Development Status :: 3 - Alpha
Classifier: Intended Audience :: Science/Research
Classifier: Programming Language :: Python :: 3
Classifier: Programming Language :: Python :: 3.8
Classifier: Programming Language :: Python :: 3.9
Classifier: Programming Language :: Python :: 3.10
Classifier: Programming Language :: Python :: 3.11
Classifier: Operating System :: OS Independent
Requires-Python: >=3.8
Requires-Dist: torch>=1.12.0
Requires-Dist: numpy>=1.21.0
Requires-Dist: scikit-learn>=1.0.0
Provides-Extra: yolo
Requires-Dist: ultralytics>=8.1.0; extra == "yolo"
Provides-Extra: vision
Requires-Dist: torchvision>=0.13.0; extra == "vision"
Requires-Dist: Pillow>=9.0.0; extra == "vision"
Provides-Extra: dev
Requires-Dist: pytest; extra == "dev"
Requires-Dist: build; extra == "dev"
Dynamic: author
Dynamic: home-page
Dynamic: requires-python
